datafunctions/__init__.py
datafunctions/datafunctions.py
datafunctions/version.py
datafunctions-0.0.1.dist-info/LICENSE.txt
datafunctions-0.0.1.dist-info/METADATA
datafunctions-0.0.1.dist-info/WHEEL
datafunctions-0.0.1.dist-info/top_level.txt
datafunctions-0.0.1.dist-info/RECORD
