Metadata-Version: 2.1
Name: datafunctions
Version: 0.0.1
Summary: Automatic (de)serialization of arguments and return values
Home-page: http://github.com/alexmojaki/datafunctions
Author: Alex Hall
Author-email: alex.mojaki@gmail.com
License: MIT
Platform: UNKNOWN
Classifier: Intended Audience :: Developers
Classifier: Programming Language :: Python :: 3
Classifier: Programming Language :: Python :: 3.7
Classifier: Programming Language :: Python :: 3.8
Classifier: License :: OSI Approved :: MIT License
Classifier: Operating System :: OS Independent
Requires-Dist: marshmallow
Requires-Dist: marshmallow-dataclass
Provides-Extra: tests
Requires-Dist: pytest ; extra == 'tests'
